[{"text":"你好","file":"w0001.mp3"},{"text":"您好","file":"w0002.mp3"},{"text":"早上好","file":"w0003.mp3"},{"text":"晚上好","file":"w0004.mp3"},{"text":"再见","file":"w0005.mp3"},{"text":"明天见","file":"w0006.mp3"},{"text":"你好吗","file":"w0007.mp3"},{"text":"我很好","file":"w0008.mp3"},{"text":"谢谢","file":"w0009.mp3"},{"text":"不客气","file":"w0010.mp3"},{"text":"对不起","file":"w0011.mp3"},{"text":"没关系","file":"w0012.mp3"},{"text":"请","file":"w0013.mp3"},{"text":"请问","file":"w0014.mp3"},{"text":"没问题","file":"w0015.mp3"},{"text":"我","file":"w0016.mp3"},{"text":"你","file":"w0017.mp3"},{"text":"叫","file":"w0018.mp3"},{"text":"什么","file":"w0019.mp3"},{"text":"名字","file":"w0020.mp3"},{"text":"认识","file":"w0021.mp3"},{"text":"高兴","file":"w0022.mp3"},{"text":"他","file":"w0023.mp3"},{"text":"她","file":"w0024.mp3"},{"text":"它","file":"w0025.mp3"},{"text":"我们","file":"w0026.mp3"},{"text":"你们","file":"w0027.mp3"},{"text":"他们","file":"w0028.mp3"},{"text":"爸爸","file":"w0029.mp3"},{"text":"妈妈","file":"w0030.mp3"},{"text":"哥哥","file":"w0031.mp3"},{"text":"姐姐","file":"w0032.mp3"},{"text":"弟弟","file":"w0033.mp3"},{"text":"妹妹","file":"w0034.mp3"},{"text":"家","file":"w0035.mp3"},{"text":"爱","file":"w0036.mp3"},{"text":"中国","file":"w0037.mp3"},{"text":"俄罗斯","file":"w0038.mp3"},{"text":"美国","file":"w0039.mp3"},{"text":"人","file":"w0040.mp3"},{"text":"中文","file":"w0041.mp3"},{"text":"英文","file":"w0042.mp3"},{"text":"会","file":"w0043.mp3"},{"text":"零","file":"w0044.mp3"},{"text":"一","file":"w0045.mp3"},{"text":"二","file":"w0046.mp3"},{"text":"三","file":"w0047.mp3"},{"text":"四","file":"w0048.mp3"},{"text":"五","file":"w0049.mp3"},{"text":"六","file":"w0050.mp3"},{"text":"七","file":"w0051.mp3"},{"text":"八","file":"w0052.mp3"},{"text":"九","file":"w0053.mp3"},{"text":"十","file":"w0054.mp3"},{"text":"星期","file":"w0055.mp3"},{"text":"星期一","file":"w0056.mp3"},{"text":"星期三","file":"w0057.mp3"},{"text":"星期五","file":"w0058.mp3"},{"text":"星期日","file":"w0059.mp3"},{"text":"今天","file":"w0060.mp3"},{"text":"明天","file":"w0061.mp3"},{"text":"昨天","file":"w0062.mp3"},{"text":"现在","file":"w0063.mp3"},{"text":"点","file":"w0064.mp3"},{"text":"分","file":"w0065.mp3"},{"text":"半","file":"w0066.mp3"},{"text":"上午","file":"w0067.mp3"},{"text":"下午","file":"w0068.mp3"},{"text":"几点","file":"w0069.mp3"},{"text":"是","file":"w0070.mp3"},{"text":"有","file":"w0071.mp3"},{"text":"在","file":"w0072.mp3"},{"text":"想","file":"w0073.mp3"},{"text":"要","file":"w0074.mp3"},{"text":"不","file":"w0075.mp3"},{"text":"没","file":"w0076.mp3"},{"text":"去","file":"w0077.mp3"},{"text":"来","file":"w0078.mp3"},{"text":"吃","file":"w0079.mp3"},{"text":"喝","file":"w0080.mp3"},{"text":"看","file":"w0081.mp3"},{"text":"说","file":"w0082.mp3"},{"text":"学习","file":"w0083.mp3"},{"text":"工作","file":"w0084.mp3"},{"text":"喜欢","file":"w0085.mp3"},{"text":"朋友","file":"w0086.mp3"},{"text":"音乐","file":"w0087.mp3"},{"text":"电影","file":"w0088.mp3"},{"text":"很","file":"w0089.mp3"},{"text":"也","file":"w0090.mp3"},{"text":"米饭","file":"w0091.mp3"},{"text":"面条","file":"w0092.mp3"},{"text":"水","file":"w0093.mp3"},{"text":"茶","file":"w0094.mp3"},{"text":"咖啡","file":"w0095.mp3"},{"text":"苹果","file":"w0096.mp3"},{"text":"鸡蛋","file":"w0097.mp3"},{"text":"好吃","file":"w0098.mp3"},{"text":"红色","file":"w0099.mp3"},{"text":"蓝色","file":"w0100.mp3"},{"text":"白色","file":"w0101.mp3"},{"text":"黑色","file":"w0102.mp3"},{"text":"绿色","file":"w0103.mp3"},{"text":"黄色","file":"w0104.mp3"},{"text":"颜色","file":"w0105.mp3"},{"text":"钱","file":"w0106.mp3"},{"text":"多少","file":"w0107.mp3"},{"text":"块","file":"w0108.mp3"},{"text":"买","file":"w0109.mp3"},{"text":"这个","file":"w0110.mp3"},{"text":"那个","file":"w0111.mp3"},{"text":"贵","file":"w0112.mp3"},{"text":"便宜","file":"w0113.mp3"},{"text":"谁","file":"w0114.mp3"},{"text":"哪儿","file":"w0115.mp3"},{"text":"几","file":"w0116.mp3"},{"text":"怎么","file":"w0117.mp3"},{"text":"为什么","file":"w0118.mp3"},{"text":"吗","file":"w0119.mp3"},{"text":"的","file":"w0120.mp3"},{"text":"呢","file":"w0121.mp3"},{"text":"了","file":"w0122.mp3"},{"text":"和","file":"w0123.mp3"},{"text":"都","file":"w0124.mp3"},{"text":"个","file":"w0125.mp3"},{"text":"本","file":"w0126.mp3"},{"text":"杯","file":"w0127.mp3"},{"text":"两","file":"w0128.mp3"},{"text":"书","file":"w0129.mp3"},{"text":"你好！你好吗？","file":"w0130.mp3"},{"text":"我很好，谢谢。","file":"w0131.mp3"},{"text":"再见，明天见！","file":"w0132.mp3"},{"text":"谢谢你！  不客气。","file":"w0133.mp3"},{"text":"对不起。  没关系。","file":"w0134.mp3"},{"text":"请问，你叫什么名字？","file":"w0135.mp3"},{"text":"你叫什么名字？","file":"w0136.mp3"},{"text":"我叫 ___。","file":"w0137.mp3"},{"text":"认识你很高兴！","file":"w0138.mp3"},{"text":"他是我朋友。","file":"w0139.mp3"},{"text":"我们是学生。","file":"w0140.mp3"},{"text":"这是我妈妈。","file":"w0141.mp3"},{"text":"我爱我的家。","file":"w0142.mp3"},{"text":"我是俄罗斯人。","file":"w0143.mp3"},{"text":"我会说一点儿中文。","file":"w0144.mp3"},{"text":"三 + 四 = 七","file":"w0145.mp3"},{"text":"我有两个哥哥。","file":"w0146.mp3"},{"text":"今天星期几？","file":"w0147.mp3"},{"text":"明天是星期五。","file":"w0148.mp3"},{"text":"现在几点？","file":"w0149.mp3"},{"text":"现在三点半。","file":"w0150.mp3"},{"text":"我是学生。","file":"w0151.mp3"},{"text":"我没有时间。","file":"w0152.mp3"},{"text":"我想喝茶。","file":"w0153.mp3"},{"text":"我去学校。","file":"w0154.mp3"},{"text":"你想吃什么？","file":"w0155.mp3"},{"text":"我很喜欢音乐。","file":"w0156.mp3"},{"text":"我也喜欢你。","file":"w0157.mp3"},{"text":"我要一杯咖啡。","file":"w0158.mp3"},{"text":"这个面条很好吃。","file":"w0159.mp3"},{"text":"我喜欢蓝色。","file":"w0160.mp3"},{"text":"这是红色的花。","file":"w0161.mp3"},{"text":"这个多少钱？","file":"w0162.mp3"},{"text":"太贵了！","file":"w0163.mp3"},{"text":"你去哪儿？","file":"w0164.mp3"},{"text":"这是谁？","file":"w0165.mp3"},{"text":"你是老师吗？","file":"w0166.mp3"},{"text":"我很好，你呢？","file":"w0167.mp3"},{"text":"我要两个苹果。","file":"w0168.mp3"},{"text":"我有三本书。","file":"w0169.mp3"},{"text":"妈","file":"w0170.mp3"},{"text":"麻","file":"w0171.mp3"},{"text":"马","file":"w0172.mp3"},{"text":"骂","file":"w0173.mp3"},{"text":"拔","file":"w0174.mp3"},{"text":"把","file":"w0175.mp3"},{"text":"爸","file":"w0176.mp3"},{"text":"汤","file":"w0177.mp3"},{"text":"糖","file":"w0178.mp3"},{"text":"躺","file":"w0179.mp3"},{"text":"烫","file":"w0180.mp3"},{"text":"怕","file":"w0181.mp3"},{"text":"肚","file":"w0182.mp3"},{"text":"兔","file":"w0183.mp3"},{"text":"古","file":"w0184.mp3"},{"text":"苦","file":"w0185.mp3"},{"text":"鸡","file":"w0186.mp3"},{"text":"西","file":"w0187.mp3"},{"text":"知","file":"w0188.mp3"},{"text":"师","file":"w0189.mp3"},{"text":"早","file":"w0190.mp3"},{"text":"草","file":"w0191.mp3"},{"text":"嫂","file":"w0192.mp3"},{"text":"桑","file":"w0193.mp3"},{"text":"心","file":"w0194.mp3"},{"text":"星","file":"w0195.mp3"},{"text":"真","file":"w0196.mp3"},{"text":"争","file":"w0197.mp3"},{"text":"很好","file":"w0198.mp3"},{"text":"可以","file":"w0199.mp3"},{"text":"老鼠","file":"w0200.mp3"},{"text":"不是","file":"w0201.mp3"},{"text":"不要","file":"w0202.mp3"},{"text":"不对","file":"w0203.mp3"},{"text":"不好","file":"w0204.mp3"},{"text":"一个","file":"w0205.mp3"},{"text":"一样","file":"w0206.mp3"},{"text":"一天","file":"w0207.mp3"},{"text":"一起","file":"w0208.mp3"},{"text":"你好！","file":"w0209.mp3"},{"text":"我叫李娜。你呢？","file":"w0210.mp3"},{"text":"我叫王明。","file":"w0211.mp3"},{"text":"你家有几个人？","file":"w0212.mp3"},{"text":"我家有四个人。","file":"w0213.mp3"},{"text":"们","file":"w0214.mp3"},{"text":"口","file":"w0215.mp3"},{"text":"女","file":"w0216.mp3"},{"text":"好","file":"w0217.mp3"},{"text":"姐","file":"w0218.mp3"},{"text":"子","file":"w0219.mp3"},{"text":"字","file":"w0220.mp3"},{"text":"学","file":"w0221.mp3"},{"text":"河","file":"w0222.mp3"},{"text":"洗","file":"w0223.mp3"},{"text":"火","file":"w0224.mp3"},{"text":"热","file":"w0225.mp3"},{"text":"灯","file":"w0226.mp3"},{"text":"木","file":"w0227.mp3"},{"text":"林","file":"w0228.mp3"},{"text":"森","file":"w0229.mp3"},{"text":"桌","file":"w0230.mp3"},{"text":"忙","file":"w0231.mp3"},{"text":"快","file":"w0232.mp3"},{"text":"手","file":"w0233.mp3"},{"text":"打","file":"w0234.mp3"},{"text":"找","file":"w0235.mp3"},{"text":"拿","file":"w0236.mp3"},{"text":"日","file":"w0237.mp3"},{"text":"明","file":"w0238.mp3"},{"text":"时","file":"w0239.mp3"},{"text":"月","file":"w0240.mp3"},{"text":"朋","file":"w0241.mp3"},{"text":"期","file":"w0242.mp3"},{"text":"目","file":"w0243.mp3"},{"text":"睡","file":"w0244.mp3"},{"text":"言","file":"w0245.mp3"},{"text":"语","file":"w0246.mp3"},{"text":"谢","file":"w0247.mp3"},{"text":"食","file":"w0248.mp3"},{"text":"饭","file":"w0249.mp3"},{"text":"饿","file":"w0250.mp3"},{"text":"馆","file":"w0251.mp3"},{"text":"土","file":"w0252.mp3"},{"text":"地","file":"w0253.mp3"},{"text":"大","file":"w0254.mp3"},{"text":"天","file":"w0255.mp3"},{"text":"太","file":"w0256.mp3"},{"text":"山","file":"w0257.mp3"},{"text":"出","file":"w0258.mp3"},{"text":"岁","file":"w0259.mp3"},{"text":"田","file":"w0260.mp3"},{"text":"男","file":"w0261.mp3"},{"text":"画","file":"w0262.mp3"},{"text":"门","file":"w0263.mp3"},{"text":"问","file":"w0264.mp3"},{"text":"间","file":"w0265.mp3"},{"text":"一个人","file":"w0266.mp3"},{"text":"一本书","file":"w0267.mp3"},{"text":"只","file":"w0268.mp3"},{"text":"一只猫","file":"w0269.mp3"},{"text":"张","file":"w0270.mp3"},{"text":"一张纸","file":"w0271.mp3"},{"text":"一杯水","file":"w0272.mp3"},{"text":"位","file":"w0273.mp3"},{"text":"一位老师","file":"w0274.mp3"},{"text":"件","file":"w0275.mp3"},{"text":"一件衣服","file":"w0276.mp3"},{"text":"条","file":"w0277.mp3"},{"text":"一条鱼","file":"w0278.mp3"},{"text":"一块钱","file":"w0279.mp3"},{"text":"双","file":"w0280.mp3"},{"text":"一双鞋","file":"w0281.mp3"},{"text":"你好世界","file":"w0282.mp3"}]